pyB12MPS/__init__.py
pyB12MPS/mps.py
pyB12MPS/version.py
pyB12MPS-2.0.0.dist-info/LICENSE.txt
pyB12MPS-2.0.0.dist-info/METADATA
pyB12MPS-2.0.0.dist-info/WHEEL
pyB12MPS-2.0.0.dist-info/top_level.txt
pyB12MPS-2.0.0.dist-info/RECORD
