Metadata-Version: 2.1
Name: pyB12MPS
Version: 2.0.0
Summary: A Python Package for Interfacing with the Bridge12 MPS
Home-page: http://www.bridge12.com/
Author: Bridge12 Technologies, Inc
Author-email: tkeller@bridge12.com
Project-URL: Source Code, https://github.com/Bridge12Technologies/pyB12MPS
Project-URL: Documentation, http://pyb12mps.bridge12.com
Classifier: Programming Language :: Python :: 3
Classifier: License :: OSI Approved :: MIT License
Classifier: Operating System :: OS Independent
Requires-Python: >=3.6
License-File: LICENSE.txt
Requires-Dist: numpy
Requires-Dist: pyserial
